sitePS_dabaixian/__init__.py
sitePS_dabaixian/main.py
sitePS_dabaixian/preprocess2csv.py
sitePS_dabaixian/sites_add_PS.py
sitePS_dabaixian-0.0.1.dist-info/LICENSE
sitePS_dabaixian-0.0.1.dist-info/METADATA
sitePS_dabaixian-0.0.1.dist-info/WHEEL
sitePS_dabaixian-0.0.1.dist-info/top_level.txt
sitePS_dabaixian-0.0.1.dist-info/RECORD
