Metadata-Version: 2.1
Name: sitePS_dabaixian
Version: 0.0.1
Summary: Phylogenetic positioning of amino acid sites in human proteins
Author-email: dabaixian <178332469@qq.com>
Project-URL: Homepage, https://github.com/tachengtatangi/Tmp
Project-URL: Issues, https://github.com/tachengtatangi/Tmp/issues
Classifier: Programming Language :: Python :: 3
Classifier: License :: OSI Approved :: MIT License
Classifier: Operating System :: OS Independent
Requires-Python: >=3.7
License-File: LICENSE
Requires-Dist: numpy
Requires-Dist: pandas >=2.1.1
